mlsys/__init__.py
mlsys-0.0.0.1.dist-info/METADATA
mlsys-0.0.0.1.dist-info/WHEEL
mlsys-0.0.0.1.dist-info/top_level.txt
mlsys-0.0.0.1.dist-info/RECORD
